src/cpu.sv
module cpu
(
    input  logic       clk,
    input  logic       rst,

    input  logic [7:0] q,
    output logic [7:0] d
);

always_ff @ (posedge clk or negedge rst) begin
    if (!rst)
        d <= 8'b0;
    else
        d <= q;
end

endmodule;

tb/dump.vcd
$version Generated by VerilatedVcd $end
$timescale 1ps $end
 $scope module $rootio $end
  $var wire 1 # clk $end
  $var wire 1 $ rst $end
  $var wire 8 % q [7:0] $end
  $var wire 8 & d [7:0] $end
 $upscope $end
 $scope module cpu $end
  $var wire 1 ' clk $end
  $var wire 1 ( rst $end
  $var wire 8 ) q [7:0] $end
  $var wire 8 * d [7:0] $end
 $upscope $end
$enddefinitions $end


#0
0#
0$
b00000000 %
b00000000 &
0'
0(
b00000000 )
b00000000 *
#1000
1#
1'
#6000
0#
0'
#11000
1#
1'
#16000
0#
1$
0'
1(
#21000
1#
1'
#26000
0#
0'
#31000
1#
b00000001 %
1'
b00000001 )
#36000
0#
0'
#41000
1#
b00000010 %
b00000001 &
1'
b00000010 )
b00000001 *
#46000
0#
0'
#51000
1#
b00000011 %
b00000010 &
1'
b00000011 )
b00000010 *
#56000
0#
0'
#61000
1#
b00000100 %
b00000011 &
1'
b00000100 )
b00000011 *
#66000
0#
0'
#71000
1#
b00000101 %
b00000100 &
1'
b00000101 )
b00000100 *
#76000
0#
0'
#81000
1#
b00000110 %
b00000101 &
1'
b00000110 )
b00000101 *
#86000
0#
0'
#91000
1#
b00000111 %
b00000110 &
1'
b00000111 )
b00000110 *
#96000
0#
0'
#101000
1#
b00001000 %
b00000111 &
1'
b00001000 )
b00000111 *
#106000
0#
0'
#111000
1#
b00001001 %
b00001000 &
1'
b00001001 )
b00001000 *
#116000
0#
0'
#121000
1#
b00001010 %
b00001001 &
1'
b00001010 )
b00001001 *
#126000
0#
0'
#131000
1#
b00001011 %
b00001010 &
1'
b00001011 )
b00001010 *
#136000
0#
0'
#141000
1#
b00001100 %
b00001011 &
1'
b00001100 )
b00001011 *
#146000
0#
0'
#151000
1#
b00001101 %
b00001100 &
1'
b00001101 )
b00001100 *
#156000
0#
0'
#161000
1#
b00001110 %
b00001101 &
1'
b00001110 )
b00001101 *
#166000
0#
0'
#171000
1#
b00001111 %
b00001110 &
1'
b00001111 )
b00001110 *
#176000
0#
0'
#181000
1#
b00010000 %
b00001111 &
1'
b00010000 )
b00001111 *
#186000
0#
0'
#191000
1#
b00010001 %
b00010000 &
1'
b00010001 )
b00010000 *
#196000
0#
0'
#201000
1#
b00010010 %
b00010001 &
1'
b00010010 )
b00010001 *
#206000
0#
0'
#211000
1#
b00010011 %
b00010010 &
1'
b00010011 )
b00010010 *
#216000
0#
0'
#221000
1#
b00010100 %
b00010011 &
1'
b00010100 )
b00010011 *
#226000
0#
0'
#231000
1#
b00010101 %
b00010100 &
1'
b00010101 )
b00010100 *
#236000
0#
0'
#241000
1#
b00010110 %
b00010101 &
1'
b00010110 )
b00010101 *
#246000
0#
0'
#251000
1#
b00010111 %
b00010110 &
1'
b00010111 )
b00010110 *
#256000
0#
0'
#261000
1#
b00011000 %
b00010111 &
1'
b00011000 )
b00010111 *
#266000
0#
0'
#271000
1#
b00011001 %
b00011000 &
1'
b00011001 )
b00011000 *
#276000
0#
0'
#281000
1#
b00011010 %
b00011001 &
1'
b00011010 )
b00011001 *
#286000
0#
0'
#291000
1#
b00011011 %
b00011010 &
1'
b00011011 )
b00011010 *
#296000
0#
0'
#301000
1#
b00011100 %
b00011011 &
1'
b00011100 )
b00011011 *
#306000
0#
0'
#311000
1#
b00011101 %
b00011100 &
1'
b00011101 )
b00011100 *
#316000
0#
0'
#321000
1#
b00011110 %
b00011101 &
1'
b00011110 )
b00011101 *
#326000
0#
0'
#331000
1#
b00011111 %
b00011110 &
1'
b00011111 )
b00011110 *
#336000
0#
0'
#341000
1#
b00011111 &
1'
b00011111 *
